{
  "$schema": "https://developer.microsoft.com/json-schemas/fabric/item/report/definition/visualContainer/2.8.0/schema.json",
  "name": "8cb15c59d8ce37c096a4",
  "position": {
    "x": 1.6666666666666667,
    "y": 403.33333333333337,
    "z": 6000,
    "height": 85,
    "width": 251.66666666666669,
    "tabOrder": 6000
  },
  "visual": {
    "visualType": "cardVisual",
    "query": {
      "queryState": {
        "Data": {
          "projections": [
            {
              "field": {
                "Measure": {
                  "Expression": {
                    "SourceRef": {
                      "Entity": "_Measures"
                    }
                  },
                  "Property": "OTS"
                }
              },
              "queryRef": "_Measures.OTS",
              "nativeQueryRef": "OTS"
            }
          ]
        }
      },
      "sortDefinition": {
        "sort": [
          {
            "field": {
              "Measure": {
                "Expression": {
                  "SourceRef": {
                    "Entity": "_Measures"
                  }
                },
                "Property": "OTS"
              }
            },
            "direction": "Descending"
          }
        ],
        "isDefaultSort": true
      }
    },
    "objects": {
      "layout": [
        {
          "properties": {
            "backgroundShow": {
              "expr": {
                "Literal": {
                  "Value": "false"
                }
              }
            }
          },
          "selector": {
            "id": "default"
          }
        }
      ],
      "outline": [
        {
          "properties": {
            "show": {
              "expr": {
                "Literal": {
                  "Value": "false"
                }
              }
            }
          },
          "selector": {
            "id": "default"
          }
        }
      ],
      "divider": [
        {
          "properties": {
            "show": {
              "expr": {
                "Literal": {
                  "Value": "false"
                }
              }
            }
          },
          "selector": {
            "id": "default"
          }
        }
      ],
      "value": [
        {
          "properties": {
            "show": {
              "expr": {
                "Literal": {
                  "Value": "true"
                }
              }
            }
          }
        }
      ],
      "label": [
        {
          "properties": {
            "show": {
              "expr": {
                "Literal": {
                  "Value": "false"
                }
              }
            }
          },
          "selector": {
            "id": "default"
          }
        }
      ]
    },
    "visualContainerObjects": {
      "title": [
        {
          "properties": {
            "show": {
              "expr": {
                "Literal": {
                  "Value": "true"
                }
              }
            },
            "text": {
              "expr": {
                "Literal": {
                  "Value": "'Impressions'"
                }
              }
            }
          }
        }
      ]
    },
    "drillFilterOtherVisuals": true
  }
}